arched_emailer/__init__.py
arched_emailer/arched_emailer.py
arched_emailer/encryption.py
arched_emailer/utils.py
arched_emailer-0.5.0.dist-info/METADATA
arched_emailer-0.5.0.dist-info/WHEEL
arched_emailer-0.5.0.dist-info/RECORD
