Metadata-Version: 2.4
Name: arched_emailer
Version: 0.5.0
Summary: A emailing python library
Project-URL: Home, https://github.com/lewis-morris/arched_emailer
Author-email: lewis <lewis@arched.dev>
License: MIT
Classifier: License :: OSI Approved :: MIT License
Classifier: Operating System :: OS Independent
Classifier: Programming Language :: Python :: 3
Requires-Python: >=3.10
Requires-Dist: appdirs==1.4.4
Requires-Dist: concurrent-log-handler>=0.9.27
Requires-Dist: flask-login==0.6.3
Requires-Dist: flask>=3.1.1
Requires-Dist: pytest-cov==6.2.1
Requires-Dist: pytest>=8.4.1
Requires-Dist: requests>=2.32.3
Requires-Dist: smtpymailer>=0.1.10
